{
  "project_info": {
    "project_number": "189012957884",
    "project_id": "tactical-lfg",
    "storage_bucket": "tactical-lfg.firebasestorage.app"
  },
  "client": [
    {
      "client_info": {
        "mobilesdk_app_id": "1:189012957884:android:7c57cdc4d0b6cce03f0eb9",
        "android_client_info": {
          "package_name": "com.seba.tacticallfg"
        }
      },
      "oauth_client": [
        {
          "client_id": "189012957884-ctrgj43cbpg54sedkkihiap0f9mr45qa.apps.googleusercontent.com",
          "client_type": 1,
          "android_info": {
            "package_name": "com.seba.tacticallfg",
            "certificate_hash": "10af1e98f3739c07e89630f10b1f10b5a7466f14"
          }
        },
        {
          "client_id": "189012957884-hjqpcrc6em297tf5e0nvae94aqmv3i1r.apps.googleusercontent.com",
          "client_type": 3
        }
      ],
      "api_key": [
        {
          "current_key": "AIzaSyBZhOaNPDwUCTB8l0DilXy_prwjo4j6RaA"
        }
      ],
      "services": {
        "appinvite_service": {
          "other_platform_oauth_client": [
            {
              "client_id": "189012957884-hjqpcrc6em297tf5e0nvae94aqmv3i1r.apps.googleusercontent.com",
              "client_type": 3
            }
          ]
        }
      }
    }
  ],
  "configuration_version": "1"
}